hboard/__init__.py
hboard/app.py
hboard/callbacks.py
hboard/cli.py
hboard/handlers.py
hboard/assets/asset-manifest.json
hboard/assets/favicon.ico
hboard/assets/index.html
hboard/assets/manifest.json
hboard/assets/static/js/2.5378a6eb.chunk.js
hboard/assets/static/js/2.5378a6eb.chunk.js.LICENSE.txt
hboard/assets/static/js/2.5378a6eb.chunk.js.map
hboard/assets/static/js/main.77edd1aa.chunk.js
hboard/assets/static/js/main.77edd1aa.chunk.js.map
hboard/assets/static/js/runtime-main.352b4b60.js
hboard/assets/static/js/runtime-main.352b4b60.js.map
hboard/tests/__init__.py
hboard/tests/app_test.py
hboard/tests/run_web_server.py
hboard-0.1.1.dist-info/METADATA
hboard-0.1.1.dist-info/WHEEL
hboard-0.1.1.dist-info/entry_points.txt
hboard-0.1.1.dist-info/top_level.txt
hboard-0.1.1.dist-info/RECORD
